mdclense/__.init__.py
mdclense/parser.py
mdclense-0.1.2.dist-info/METADATA
mdclense-0.1.2.dist-info/WHEEL
mdclense-0.1.2.dist-info/RECORD
