Metadata-Version: 2.3
Name: mdclense
Version: 0.1.2
Summary: A library for cleaning, stripping markdown and converting it to text
Project-URL: Homepage, https://github.com/boadzie/mdclense
Project-URL: Bug Tracker, https://github.com/boadzie/mdclense/issues
Author-email: Daniel Boadzie <boadziedaniel43@gmail.com>
Classifier: License :: OSI Approved :: MIT License
Classifier: Operating System :: OS Independent
Classifier: Programming Language :: Python :: 3
Requires-Python: >=3.11
